stackit_cost_monitoring/__init__.py
stackit_cost_monitoring/auth.py
stackit_cost_monitoring/cost_api.py
stackit_cost_monitoring/nagios_plugin.py
stackit_cost_monitoring-0.8.2.dist-info/LICENSE
stackit_cost_monitoring-0.8.2.dist-info/METADATA
stackit_cost_monitoring-0.8.2.dist-info/WHEEL
stackit_cost_monitoring-0.8.2.dist-info/entry_points.txt
stackit_cost_monitoring-0.8.2.dist-info/RECORD
