Metadata-Version: 2.3
Name: stackit_cost_monitoring
Version: 0.8.2
Summary: Nagios plugin to monitor cloud costs in the StackIT cloud.
License: GNU Public License v3
Author: Harald Wilhelmi
Author-email: harald.wilhelmi@uni-heidelberg.de
Requires-Python: >=3.10,<4.0
Classifier: License :: Other/Proprietary License
Classifier: Programming Language :: Python :: 3
Classifier: Programming Language :: Python :: 3.10
Classifier: Programming Language :: Python :: 3.11
Classifier: Programming Language :: Python :: 3.12
Classifier: Programming Language :: Python :: 3.13
Requires-Dist: cryptography (>=46.0.3,<47.0.0)
Requires-Dist: pydantic
Requires-Dist: pyjwt (>=2.10.1,<3.0.0)
Requires-Dist: requests (>=2.32.5,<3.0.0)
Project-URL: Homepage, https://github.com/dieterich-lab/stackit_cost_monitoring
Project-URL: Issues, https://github.com/dieterich-lab/stackit_cost_monitoring/issues
